json_explorer/__init__.py
json_explorer/__main__.py
json_explorer/cli.py
json_explorer/explore.py
json_explorer/style.css
json_explorer/template.html
json_explorer-0.1.0.dist-info/LICENSE
json_explorer-0.1.0.dist-info/METADATA
json_explorer-0.1.0.dist-info/WHEEL
json_explorer-0.1.0.dist-info/entry_points.txt
json_explorer-0.1.0.dist-info/RECORD
