Metadata-Version: 2.1
Name: json-explorer
Version: 0.1.0
Summary: Explore the structure of a bunch of jsons
Home-page: https://github.com/stringertheory/json-explorer
Author: Mike Stringer
Author-email: fmike.stringer.internet@gmail.com
Requires-Python: >=3.7,<4.0
Classifier: Programming Language :: Python :: 3
Classifier: Programming Language :: Python :: 3.7
Classifier: Programming Language :: Python :: 3.8
Classifier: Programming Language :: Python :: 3.9
Classifier: Programming Language :: Python :: 3.10
Classifier: Programming Language :: Python :: 3.11
Project-URL: Documentation, https://stringertheory.github.io/json-explorer/
Project-URL: Repository, https://github.com/stringertheory/json-explorer
